{
  "version": 1,
  "saved_at": 1778740689,
  "slots": [
    {
      "hwnd": 6163090,
      "title": "(12) ‎🏆대박수익 강의실️️🏆 – (7814)",
      "class": "Qt51518QWindowIcon",
      "pid": 6684,
      "exe": "C:\\Users\\m5\\Desktop\\멀티텔레그램\\Telegram - new (11)\\Telegram.exe"
    },
    {
      "hwnd": 1182494,
      "title": "(8) ‎🏆대박수익 강의실️️🏆 @ ‎김 덕배 (189)",
      "class": "Qt51518QWindowIcon",
      "pid": 13648,
      "exe": "C:\\Users\\m5\\Desktop\\멀티텔레그램\\Telegram - new (12 13)\\Telegram.exe"
    },
    {
      "hwnd": 1574412,
      "title": "(9) ‎🏆대박수익 강의실️️🏆 @ ‎김 진숙 (189)",
      "class": "Qt51518QWindowIcon",
      "pid": 13648,
      "exe": "C:\\Users\\m5\\Desktop\\멀티텔레그램\\Telegram - new (12 13)\\Telegram.exe"
    },
    {
      "hwnd": 12322334,
      "title": "(7) ‎🏆대박수익 강의실️️🏆 @ ‎mr.bae (1625)",
      "class": "Qt51518QWindowIcon",
      "pid": 10888,
      "exe": "C:\\Users\\m5\\Desktop\\멀티텔레그램\\Telegram - new (14 15)\\Telegram.exe"
    },
    {
      "hwnd": 12323722,
      "title": "(3) ‎🏆대박수익 강의실️️🏆 @ ‎류 승태 (1625)",
      "class": "Qt51518QWindowIcon",
      "pid": 10888,
      "exe": "C:\\Users\\m5\\Desktop\\멀티텔레그램\\Telegram - new (14 15)\\Telegram.exe"
    },
    {
      "hwnd": 592412,
      "title": "(19) ‎🏆대박수익 강의실️️🏆 – (118)",
      "class": "Qt51518QWindowIcon",
      "pid": 4892,
      "exe": "C:\\Users\\m5\\Desktop\\멀티텔레그램\\Telegram - new (16)\\Telegram.exe"
    },
    {
      "hwnd": 11470592,
      "title": "(16) ‎🏆대박수익 강의실️️🏆 – (126)",
      "class": "Qt51518QWindowIcon",
      "pid": 17332,
      "exe": "C:\\Users\\m5\\Desktop\\멀티텔레그램\\Telegram - new (17)\\Telegram.exe"
    },
    {
      "hwnd": 3804426,
      "title": "(14) ‎🏆대박수익 강의실️️🏆 – (122)",
      "class": "Qt51518QWindowIcon",
      "pid": 18820,
      "exe": "C:\\Users\\m5\\Desktop\\멀티텔레그램\\Telegram - new (18)\\Telegram.exe"
    },
    {
      "hwnd": 4721942,
      "title": "(2) ‎🏆대박수익 강의실️️🏆 – (101)",
      "class": "Qt51518QWindowIcon",
      "pid": 15164,
      "exe": "C:\\Users\\m5\\Desktop\\멀티텔레그램\\Telegram - new (19)\\Telegram.exe"
    },
    null
  ]
}